setup.py
fb_down.egg-info/PKG-INFO
fb_down.egg-info/SOURCES.txt
fb_down.egg-info/dependency_links.txt
fb_down.egg-info/entry_points.txt
fb_down.egg-info/requires.txt
fb_down.egg-info/top_level.txt
fbdown/__init__.py