Metadata-Version: 1.1
Name: fb-down
Version: 1.0.1
Summary: FB Down is a simple FB Video Downloader
Home-page: https://tbhaxor.github.io/fbdown
Author: Gurkirat Singh
Author-email: tbhaxor@gmail.com
License: GNU
Keywords: gurkirat fbdown fb tbhaxor
Platform: UNKNOWN
Classifier: Development Status :: 5 - Production/Stable
Classifier: License :: OSI Approved :: GNU General Public License (GPL)
Classifier: Programming Language :: Python :: 3
Classifier: Programming Language :: Python :: 3.5
Classifier: Programming Language :: Python :: 3.6
